modelz/__init__.py
modelz/configuration_resnet.py
modelz/modeling_resnet.py
modelz/resnet.py
modelz-0.0.1.dist-info/METADATA
modelz-0.0.1.dist-info/WHEEL
modelz-0.0.1.dist-info/top_level.txt
modelz-0.0.1.dist-info/RECORD
